{
  "format_version": "1.10.0",
  "minecraft:client_entity": {
    "description": {
	
      "identifier": "myth:sell7",
      "materials": { "default": "entity_alphatest" },
      "textures": { "default": "textures/entity/sell2" },
      "geometry": { "default": "geometry.sell1" },
      "render_controllers": [ "controller.render.myth" ],
      "scripts": {
        "animate": [
		  "root"
        ]
        },
          "animations": {
		    "root":"controller.animation.myth.sell1.root",
            "idle":"animation.myth.sell.closed",
            "sell":"animation.myth.sell.output"
          },
      "spawn_egg": {
        "base_color": "#e3f3f4",
		    "overlay_color": "#95cb69"
      },
	  "sound_effects": {
		"sell": "prison.myth.sell.shop_sell"
	  }	
	  
    }
  }
}